homebase_calendar_sync/__init__.py
homebase_calendar_sync/__main__.py
homebase_calendar_sync/config.py
homebase_calendar_sync/homebase_calendar_sync.py
homebase_calendar_sync/db/__init__.py
homebase_calendar_sync/db/__main__.py
homebase_calendar_sync/db/models.py
homebase_calendar_sync/google_client/__init__.py
homebase_calendar_sync/google_client/__main__.py
homebase_calendar_sync/google_client/auth.py
homebase_calendar_sync/google_client/drive_types.py
homebase_calendar_sync/google_client/google_client.py
homebase_calendar_sync-0.1.23.dist-info/METADATA
homebase_calendar_sync-0.1.23.dist-info/WHEEL
homebase_calendar_sync-0.1.23.dist-info/entry_points.txt
homebase_calendar_sync-0.1.23.dist-info/top_level.txt
homebase_calendar_sync-0.1.23.dist-info/RECORD
